<?xml version="1.0" encoding="UTF-8"?>
<item><pubDate>Wed, 25 Jul 2012 19:17:25 +0200</pubDate><title><![CDATA[detail]]></title><url><![CDATA[detail]]></url><meta><![CDATA[]]></meta><metad><![CDATA[]]></metad><menu><![CDATA[detail]]></menu><menuOrder><![CDATA[0]]></menuOrder><menuStatus><![CDATA[Y]]></menuStatus><template><![CDATA[detail.php]]></template><parent><![CDATA[]]></parent><content><![CDATA[]]></content><private><![CDATA[]]></private><author><![CDATA[admin]]></author><creDate>Wed, 25 Jul 2012 19:17:25 +0200</creDate><user><![CDATA[admin]]></user></item>
